{"_ts":[1575166735,1575210671,1575253952],"_r":{"breakdown":{"html":{"bytes":[1670,1694,1690],"requests":[1,1,1]},"js":{"bytes":[2180,2180,2180],"requests":[3,3,3]},"css":{"bytes":[1983,1983,1983],"requests":[2,2,2]},"image":{"bytes":[323762,353736,353736],"requests":[10,11,11]},"flash":{"bytes":[0,0,0],"requests":[0,0,0]},"font":{"bytes":[0,0,0],"requests":[0,0,0]},"video":{"bytes":[1212416,1191228,1211552],"requests":[1,1,1]},"other":{"bytes":[0,0,0],"requests":[1,1,1]}},"date":[1575166735,1575210671,1575253952],"domElements":[101,103,103],"domInteractive":[477,527,465],"firstPaint":[610.4850000047,726.9450000022,624.4700000025],"fullyLoaded":[3692,3776,3791],"id":["191201_FP_ef73ba7e67f03a1bf4bbf090ca587516","191201_MQ_5520eddf0ff79677fec51f736a1a28e5","191202_A2_a5b485f5d611011e391c92aba32b7759"],"loadTime":[1054,1152,1168],"render":[600,700,600],"SpeedIndex":[600,700,604],"TTFB":[346,329,334],"videoFrames":[[{"_i":"ms_000000.jpg","_t":0,"_vc":0},{"_i":"ms_000600.jpg","_t":600,"_vc":100},{"_i":"ms_000700.jpg","_t":700,"_vc":100},{"_i":"ms_001100.jpg","_t":1100,"_vc":100},{"_i":"ms_001200.jpg","_t":1200,"_vc":100}],[{"_i":"ms_000000.jpg","_t":0,"_vc":0},{"_i":"ms_000700.jpg","_t":700,"_vc":100},{"_i":"ms_001200.jpg","_t":1200,"_vc":100},{"_i":"ms_001300.jpg","_t":1300,"_vc":100}],[{"_i":"ms_000000.jpg","_t":0,"_vc":0},{"_i":"ms_000600.jpg","_t":600,"_vc":96},{"_i":"ms_000700.jpg","_t":700,"_vc":100},{"_i":"ms_001000.jpg","_t":1000,"_vc":100},{"_i":"ms_001100.jpg","_t":1100,"_vc":100},{"_i":"ms_001200.jpg","_t":1200,"_vc":100},{"_i":"ms_001300.jpg","_t":1300,"_vc":100}]],"visualComplete":[600,700,700],"lighthouse":[54,54,54],"pagespeed":[81,79,79]}}